moviepy_layout/__init__.py
moviepy_layout/layout.py
moviepy_layout-0.1.0.dist-info/licenses/LICENSE
moviepy_layout-0.1.0.dist-info/METADATA
moviepy_layout-0.1.0.dist-info/WHEEL
moviepy_layout-0.1.0.dist-info/top_level.txt
moviepy_layout-0.1.0.dist-info/RECORD
