Metadata-Version: 2.4
Name: moviepy-layout
Version: 0.1.0
Summary: Composable layout primitives for MoviePy, with RGBA gradients and asset modes
Home-page: https://github.com/kmmhanan/moviepy-layout
Author: Kmm Hanan
Author-email: hanan@kmmhanan.com
Classifier: Programming Language :: Python :: 3
Classifier: License :: OSI Approved :: MIT License
Classifier: Topic :: Multimedia :: Video
Requires-Python: >=3.8
License-File: LICENSE
Requires-Dist: moviepy==1.0.3
Requires-Dist: numpy==2.3.2
Requires-Dist: Pillow==9.5.0
Requires-Dist: scipy==1.16.1
Dynamic: author
Dynamic: author-email
Dynamic: classifier
Dynamic: description
Dynamic: description-content-type
Dynamic: home-page
Dynamic: license-file
Dynamic: requires-dist
Dynamic: requires-python
Dynamic: summary
